mouette/__init__.py
mouette/config.py
mouette/sampling.py
mouette/attributes/__init__.py
mouette/attributes/attr_cells.py
mouette/attributes/attr_corners.py
mouette/attributes/attr_edges.py
mouette/attributes/attr_faces.py
mouette/attributes/attr_vertices.py
mouette/attributes/glob.py
mouette/attributes/interpolate.py
mouette/attributes/misc_cells.py
mouette/attributes/misc_corners.py
mouette/attributes/misc_edges.py
mouette/attributes/misc_faces.py
mouette/attributes/misc_vertices.py
mouette/attributes/uv_export.py
mouette/geometry/SphericalHarmonics.py
mouette/geometry/__init__.py
mouette/geometry/aabb.py
mouette/geometry/geometry.py
mouette/geometry/rotations.py
mouette/geometry/transform.py
mouette/geometry/vector.py
mouette/mesh/__init__.py
mouette/mesh/data_container.py
mouette/mesh/mesh.py
mouette/mesh/mesh_attributes.py
mouette/mesh/mesh_data.py
mouette/mesh/subdivision.py
mouette/mesh/datatypes/__init__.py
mouette/mesh/datatypes/base.py
mouette/mesh/datatypes/linear.py
mouette/mesh/datatypes/pointcloud.py
mouette/mesh/datatypes/surface.py
mouette/mesh/datatypes/type_checks.py
mouette/mesh/datatypes/volume.py
mouette/mesh/io/__init__.py
mouette/mesh/io/geogram_ascii.py
mouette/mesh/io/io.py
mouette/mesh/io/medit.py
mouette/mesh/io/obj.py
mouette/mesh/io/off.py
mouette/mesh/io/ply.py
mouette/mesh/io/stl.py
mouette/mesh/io/tet.py
mouette/mesh/io/xyz.py
mouette/operators/__init__.py
mouette/operators/adjacency.py
mouette/operators/gradient.py
mouette/operators/gradient_op.py
mouette/operators/laplacian_op.py
mouette/operators/mass.py
mouette/optimize/__init__.py
mouette/optimize/eigensolve.py
mouette/optimize/finite_diff.py
mouette/optimize/levenberg_marquardt.py
mouette/optimize/newton.py
mouette/procedural/__init__.py
mouette/procedural/dual.py
mouette/procedural/flat.py
mouette/procedural/polylines.py
mouette/procedural/rings.py
mouette/procedural/shapes.py
mouette/procedural/transform.py
mouette/procedural/transformations.py
mouette/processing/__init__.py
mouette-1.2.7.1.dist-info/LICENSE
mouette-1.2.7.1.dist-info/METADATA
mouette-1.2.7.1.dist-info/WHEEL
mouette-1.2.7.1.dist-info/top_level.txt
mouette-1.2.7.1.dist-info/RECORD
