Metadata-Version: 2.1
Name: mouette
Version: 1.2.7.1
Summary: Geometry Processing and mesh handling in python
Home-page: https://github.com/GCoiffier/mouette
Author: Guillaume Coiffier
License: MIT License
Project-URL: Homepage, https://github.com/GCoiffier/mouette
Project-URL: Documentation, https://GCoiffier.github.io/mouette
Classifier: Programming Language :: Python :: 3
Classifier: Operating System :: OS Independent
Requires-Python: >=3.6
License-File: LICENSE
Requires-Dist: aenum
Requires-Dist: numba
Requires-Dist: numpy
Requires-Dist: osqp >=1.0.4
Requires-Dist: pyminiply
Requires-Dist: scipy
Requires-Dist: stl-reader
Requires-Dist: tqdm
